openbotx/__init__.py
openbotx/py.typed
openbotx/version.py
openbotx/agent/__init__.py
openbotx/agent/brain.py
openbotx/agent/prompts.py
openbotx/api/__init__.py
openbotx/api/main.py
openbotx/api/schemas.py
openbotx/api/routes/__init__.py
openbotx/api/routes/logs.py
openbotx/api/routes/media.py
openbotx/api/routes/memory.py
openbotx/api/routes/messages.py
openbotx/api/routes/providers.py
openbotx/api/routes/scheduler.py
openbotx/api/routes/skills.py
openbotx/api/routes/system.py
openbotx/api/routes/tools.py
openbotx/cli/__init__.py
openbotx/cli/commands.py
openbotx/core/__init__.py
openbotx/core/attachments.py
openbotx/core/context_store.py
openbotx/core/message_bus.py
openbotx/core/orchestrator.py
openbotx/core/security.py
openbotx/core/skills_registry.py
openbotx/core/telemetry.py
openbotx/core/tools_registry.py
openbotx/helpers/__init__.py
openbotx/helpers/config.py
openbotx/helpers/gateway_loader.py
openbotx/helpers/llm_model.py
openbotx/helpers/logger.py
openbotx/helpers/provider_loader.py
openbotx/helpers/tokens.py
openbotx/models/__init__.py
openbotx/models/enums.py
openbotx/models/job.py
openbotx/models/message.py
openbotx/models/response.py
openbotx/models/skill.py
openbotx/models/tool.py
openbotx/models/tool_result.py
openbotx/providers/__init__.py
openbotx/providers/base.py
openbotx/providers/database/__init__.py
openbotx/providers/database/base.py
openbotx/providers/database/sqlite.py
openbotx/providers/filesystem/__init__.py
openbotx/providers/filesystem/base.py
openbotx/providers/filesystem/local.py
openbotx/providers/gateway/__init__.py
openbotx/providers/gateway/base.py
openbotx/providers/gateway/cli.py
openbotx/providers/gateway/telegram.py
openbotx/providers/gateway/websocket.py
openbotx/providers/mcp/__init__.py
openbotx/providers/mcp/base.py
openbotx/providers/mcp/client.py
openbotx/providers/scheduler/__init__.py
openbotx/providers/scheduler/base.py
openbotx/providers/scheduler/cron.py
openbotx/providers/storage/__init__.py
openbotx-0.0.1.dist-info/licenses/LICENSE
openbotx-0.0.1.dist-info/METADATA
openbotx-0.0.1.dist-info/WHEEL
openbotx-0.0.1.dist-info/entry_points.txt
openbotx-0.0.1.dist-info/top_level.txt
openbotx-0.0.1.dist-info/RECORD
