Metadata-Version: 2.4
Name: openbotx
Version: 0.0.1
Summary: Your Personal AI assistant for any OS and any platform
Author-email: Paulo Coutinho <paulocoutinhox@gmail.com>
Maintainer-email: Paulo Coutinho <paulocoutinhox@gmail.com>
License: MIT
Project-URL: Homepage, https://github.com/openbotx/openbotx
Project-URL: Repository, https://github.com/openbotx/openbotx
Project-URL: Documentation, https://github.com/openbotx/openbotx
Project-URL: Bug Tracker, https://github.com/openbotx/openbotx/issues
Keywords: ai,agent,assistant,personal,bot,llm,pydantic,pydantic-ai,skills,chatbot,telegram,websocket,mcp,anthropic,openai
Requires-Python: <3.14,>=3.11
License-File: LICENSE
Requires-Dist: pydantic>=2.12.5
Requires-Dist: pydantic-ai>=1.50.0
Requires-Dist: python-dotenv>=1.2.1
Requires-Dist: pyyaml>=6.0.3
Requires-Dist: fastapi>=0.128.0
Requires-Dist: uvicorn[standard]>=0.40.0
Requires-Dist: httpx>=0.28.1
Requires-Dist: sqlalchemy>=2.0.46
Requires-Dist: aiosqlite>=0.22.1
Requires-Dist: websockets<16.0
Requires-Dist: python-telegram-bot>=22.6
Requires-Dist: anthropic>=0.77.0
Requires-Dist: openai>=2.16.0
Requires-Dist: apscheduler>=3.11.2
Requires-Dist: faster-whisper>=1.2.1
Requires-Dist: soundfile>=0.13.1
Requires-Dist: pillow>=11.0.0
Requires-Dist: boto3>=1.42.38
Requires-Dist: mcp>=1.26.0
Requires-Dist: tiktoken>=0.12.0
Requires-Dist: structlog>=25.5.0
Requires-Dist: click>=8.3.1
Requires-Dist: rich>=14.3.1
Provides-Extra: dev
Requires-Dist: pytest>=9.0.2; extra == "dev"
Requires-Dist: pytest-asyncio>=1.3.0; extra == "dev"
Requires-Dist: pytest-cov>=7.0.0; extra == "dev"
Requires-Dist: ruff>=0.14.14; extra == "dev"
Requires-Dist: mypy>=1.19.1; extra == "dev"
Requires-Dist: build>=1.4.0; extra == "dev"
Requires-Dist: twine>=6.2.0; extra == "dev"
Dynamic: license-file
